{ "TripList": {"CurrentTime": 1413261593,"Line": "Red", "Trips": [{"TripID": "24625354", "Destination": "Braintree", "Position": {"Timestamp": 1413261553, "Train": "1639", "Lat": 42.23131, "Long": -71.00711,"Heading": 180}, "Predictions": [
{"StopID": "70105", "Stop": "Braintree", "Seconds": 194}]},
{"TripID": "24625324", "Destination": "Alewife", "Position": {"Timestamp": 1413261507, "Train": "1862", "Lat": 42.35526, "Long": -71.06016,"Heading": 310}, "Predictions": [
{"StopID": "70076", "Stop": "Park Street", "Seconds": -15},
{"StopID": "70074", "Stop": "Charles/MGH", "Seconds": 100},
{"StopID": "70072", "Stop": "Kendall/MIT", "Seconds": 241},
{"StopID": "70070", "Stop": "Central Square", "Seconds": 384},
{"StopID": "70068", "Stop": "Harvard Square", "Seconds": 572},
{"StopID": "70066", "Stop": "Porter Square", "Seconds": 751},
{"StopID": "70064", "Stop": "Davis", "Seconds": 864},
{"StopID": "70061", "Stop": "Alewife", "Seconds": 1021}]},
{"TripID": "24625334", "Destination": "Alewife", "Position": {"Timestamp": 1413261573, "Train": "1800", "Lat": 42.36703, "Long": -71.10626,"Heading": 310}, "Predictions": [
{"StopID": "70068", "Stop": "Harvard Square", "Seconds": 104},
{"StopID": "70066", "Stop": "Porter Square", "Seconds": 283},
{"StopID": "70064", "Stop": "Davis", "Seconds": 396},
{"StopID": "70061", "Stop": "Alewife", "Seconds": 553}]},
{"TripID": "24625294", "Destination": "Alewife", "Position": {"Timestamp": 1413261551, "Train": "1869", "Lat": 42.3028, "Long": -71.05578,"Heading": 5}, "Predictions": [
{"StopID": "70088", "Stop": "Savin Hill", "Seconds": 15},
{"StopID": "70086", "Stop": "JFK/UMass", "Seconds": 145},
{"StopID": "70084", "Stop": "Andrew", "Seconds": 291},
{"StopID": "70082", "Stop": "Broadway", "Seconds": 416},
{"StopID": "70080", "Stop": "South Station", "Seconds": 566},
{"StopID": "70078", "Stop": "Downtown Crossing", "Seconds": 646},
{"StopID": "70076", "Stop": "Park Street", "Seconds": 717},
{"StopID": "70074", "Stop": "Charles/MGH", "Seconds": 832},
{"StopID": "70072", "Stop": "Kendall/MIT", "Seconds": 973},
{"StopID": "70070", "Stop": "Central Square", "Seconds": 1116}]},
{"TripID": "24625370", "Destination": "Braintree", "Position": {"Timestamp": 1413261572, "Train": "1839", "Lat": 42.34064, "Long": -71.05708,"Heading": 175}, "Predictions": [
{"StopID": "70083", "Stop": "Andrew", "Seconds": 34},
{"StopID": "70095", "Stop": "JFK/UMass", "Seconds": 179},
{"StopID": "70097", "Stop": "North Quincy", "Seconds": 640},
{"StopID": "70099", "Stop": "Wollaston", "Seconds": 755},
{"StopID": "70101", "Stop": "Quincy Center", "Seconds": 918},
{"StopID": "70103", "Stop": "Quincy Adams", "Seconds": 1089}]},
{"TripID": "24625364", "Destination": "Braintree", "Position": {"Timestamp": 1413261518, "Train": "1700", "Lat": 42.31602, "Long": -71.05206,"Heading": 170}, "Predictions": [
{"StopID": "70097", "Stop": "North Quincy", "Seconds": 309},
{"StopID": "70099", "Stop": "Wollaston", "Seconds": 424},
{"StopID": "70101", "Stop": "Quincy Center", "Seconds": 587},
{"StopID": "70103", "Stop": "Quincy Adams", "Seconds": 756},
{"StopID": "70105", "Stop": "Braintree", "Seconds": 1004}]},
{"TripID": "24625283", "Destination": "Ashmont", "Position": {"Timestamp": 1413261550, "Train": "1640", "Lat": 42.32057, "Long": -71.05259,"Heading": 170}, "Predictions": [
{"StopID": "70087", "Stop": "Savin Hill", "Seconds": 92},
{"StopID": "70089", "Stop": "Fields Corner", "Seconds": 268},
{"StopID": "70091", "Stop": "Shawmut", "Seconds": 388},
{"StopID": "70093", "Stop": "Ashmont", "Seconds": 533}]},
{"TripID": "24625290", "Destination": "Ashmont", "Position": {"Timestamp": 1413261485, "Train": "1708", "Lat": 42.36553, "Long": -71.10403,"Heading": 130}, "Predictions": [
{"StopID": "70071", "Stop": "Kendall/MIT", "Seconds": 42},
{"StopID": "70073", "Stop": "Charles/MGH", "Seconds": 185},
{"StopID": "70075", "Stop": "Park Street", "Seconds": 298},
{"StopID": "70077", "Stop": "Downtown Crossing", "Seconds": 379},
{"StopID": "70079", "Stop": "South Station", "Seconds": 462},
{"StopID": "70081", "Stop": "Broadway", "Seconds": 594},
{"StopID": "70083", "Stop": "Andrew", "Seconds": 719},
{"StopID": "70085", "Stop": "JFK/UMass", "Seconds": 864},
{"StopID": "70087", "Stop": "Savin Hill", "Seconds": 999},
{"StopID": "70089", "Stop": "Fields Corner", "Seconds": 1175}]},
{"TripID": "24625341", "Destination": "Alewife", "Position": {"Timestamp": 1413261523, "Train": "1804", "Lat": 42.31791, "Long": -71.05201,"Heading": 0}, "Predictions": [
{"StopID": "70096", "Stop": "JFK/UMass", "Seconds": -3},
{"StopID": "70084", "Stop": "Andrew", "Seconds": 159},
{"StopID": "70082", "Stop": "Broadway", "Seconds": 284},
{"StopID": "70080", "Stop": "South Station", "Seconds": 434},
{"StopID": "70078", "Stop": "Downtown Crossing", "Seconds": 514},
{"StopID": "70076", "Stop": "Park Street", "Seconds": 585},
{"StopID": "70074", "Stop": "Charles/MGH", "Seconds": 700},
{"StopID": "70072", "Stop": "Kendall/MIT", "Seconds": 841},
{"StopID": "70070", "Stop": "Central Square", "Seconds": 984},
{"StopID": "70068", "Stop": "Harvard Square", "Seconds": 1172}]}]}}